<?xml version="1.0" encoding="UTF-8"?>
<tmc-illust ai_version="11.0"><indicateinfo lang="english" name=""><layer artworkknockout="2" blendingmode="0" dimplacedimages="0" isisolated="0" locked="0" name="IndicateLayer" opacity="100" preview="-1" printable="-1" sliced="0" visible="-1"><pathitem artworkknockout="0" blendingmode="0" closed="-1" evenodd="0" filled="0" guides="0" height="12.75634765625" hidden="0" isisolated="0" left="236.75390625" locked="0" name="" note="" opacity="100" anchor="258.388671875,-105.92919921875/247.7587890625,-112.30712890625/237.12890625,-105.92919921875/247.7587890625,-99.55078125/" leftdirection="258.388671875,-102.40625/253.6298828125,-112.30712890625/237.12890625,-109.45166015625/241.888671875,-99.55078125/" rightdirection="258.388671875,-109.45166015625/241.888671875,-112.30712890625/237.12890625,-102.40625/253.6298828125,-99.55078125/" pointtype="1/1/1/1/" polarity="1" sliced="0" stroked="-1" strokecap="1" strokecolor="2" strokegraycolor="100" strokedashes="" strokedashoffset="0" strokejoin="1" strokemiterlimit="4" strokeoverprint="0" strokewidth="0.75" top="-99.17578125" url="" width="21.259765625"/><textart artworkknockout="0" blendingmode="0" hidden="0" isisolated="0" left="241.62890625" locked="0" name="" opacity="100" position="241.62890625,-99.90771484375" sliced="0" top="-99.90771484375" url="" height="12.04297" width="14.45215" kind="2" wrapped="0" autokerning="-1" baselineshift="0" direction="1" fillcmykcolor="0,0,0,100" fillcolor="1" filled="-1" font="ArialMT" leading="12" size="10" tracking="0">1E</textart><textart artworkknockout="0" blendingmode="0" hidden="0" isisolated="0" left="272.197265625" locked="0" name="" opacity="100" position="272.197265625,-169.3486328125" sliced="0" top="-169.3486328125" url="" height="12.31738" width="9.764648" kind="2" wrapped="0" autokerning="-1" baselineshift="0" direction="1" fillcmykcolor="0,0,0,100" fillcolor="1" filled="-1" font="ArialMT" leading="12" size="10" tracking="0">7</textart><textart artworkknockout="0" blendingmode="0" hidden="0" isisolated="0" left="161.98974609375" locked="0" name="" opacity="100" position="161.99267578125,-167.759765625" sliced="0" top="-167.759765625" url="" height="11.04199" width="11.7627" kind="2" wrapped="0" autokerning="-1" baselineshift="0" direction="1" fillcmykcolor="0,0,0,100" fillcolor="1" filled="-1" font="ArialMT" leading="12" size="10" tracking="0">3</textart><textart artworkknockout="0" blendingmode="0" hidden="0" isisolated="0" left="233.6669921875" locked="0" name="" opacity="100" position="233.6669921875,-170.0712890625" sliced="0" top="-170.0712890625" url="" height="9.041992" width="12.47754" kind="2" wrapped="0" autokerning="-1" baselineshift="0" direction="1" fillcmykcolor="0,0,0,100" fillcolor="1" filled="-1" font="ArialMT" leading="12" size="10" tracking="0">10</textart><textart artworkknockout="0" blendingmode="0" hidden="0" isisolated="0" left="130.19580078125" locked="0" name="" opacity="100" position="130.19580078125,-167.6552734375" sliced="0" top="-167.6552734375" url="" height="9.041016" width="12.11621" kind="2" wrapped="0" autokerning="-1" baselineshift="0" direction="1" fillcmykcolor="0,0,0,100" fillcolor="1" filled="-1" font="ArialMT" leading="12" size="10" tracking="0">4</textart><pathitem artworkknockout="0" blendingmode="0" closed="0" evenodd="0" filled="0" guides="0" height="56.5556640625" hidden="0" isisolated="0" left="135.25244140625" locked="0" name="" note="" opacity="100" anchor="145.912109375,-109.2900390625/135.62158203125,-165.845703125/" leftdirection="145.912109375,-109.2900390625/135.62158203125,-165.845703125/" rightdirection="145.912109375,-109.2900390625/135.62158203125,-165.845703125/" pointtype="1/1/" polarity="1" sliced="0" stroked="-1" strokecap="1" strokecolor="1" strokecmykcolor="0,0,0,100" strokedashes="" strokedashoffset="0" strokejoin="1" strokemiterlimit="4" strokeoverprint="0" strokewidth="0.75" top="-109.22314453125" url="" width="10.29052734375"/><pathitem artworkknockout="0" blendingmode="0" closed="0" evenodd="0" filled="0" guides="0" height="40.14697265625" hidden="0" isisolated="0" left="238.1787109375" locked="0" name="" note="" opacity="100" anchor="243.794921875,-129.92431640625/238.55078125,-170.0712890625/" leftdirection="243.794921875,-129.92431640625/238.55078125,-170.0712890625/" rightdirection="243.794921875,-129.92431640625/238.55078125,-170.0712890625/" pointtype="1/1/" polarity="1" sliced="0" stroked="-1" strokecap="1" strokecolor="1" strokecmykcolor="0,0,0,100" strokedashes="" strokedashoffset="0" strokejoin="1" strokemiterlimit="4" strokeoverprint="0" strokewidth="0.75" top="-129.8759765625" url="" width="5.244140625"/><pathitem artworkknockout="0" blendingmode="0" closed="0" evenodd="0" filled="0" guides="0" height="56.7802734375" hidden="0" isisolated="0" left="150.5380859375" locked="0" name="" note="" opacity="100" anchor="150.9033203125,-109.89453125/163.98193359375,-166.6748046875/" leftdirection="150.9033203125,-109.89453125/163.98193359375,-166.6748046875/" rightdirection="150.9033203125,-109.89453125/163.98193359375,-166.6748046875/" pointtype="1/1/" polarity="1" sliced="0" stroked="-1" strokecap="1" strokecolor="1" strokecmykcolor="0,0,0,100" strokedashes="" strokedashoffset="0" strokejoin="1" strokemiterlimit="4" strokeoverprint="0" strokewidth="0.75" top="-109.810546875" url="" width="13.07861328125"/><pathitem artworkknockout="0" blendingmode="0" closed="0" evenodd="0" filled="0" guides="0" height="36.98193359375" hidden="0" isisolated="0" left="258.6357421875" locked="0" name="" note="" opacity="100" anchor="258.9853515625,-130.82861328125/273.36328125,-167.810546875/" leftdirection="258.9853515625,-130.82861328125/273.36328125,-167.810546875/" rightdirection="258.9853515625,-130.82861328125/273.36328125,-167.810546875/" pointtype="1/1/" polarity="1" sliced="0" stroked="-1" strokecap="1" strokecolor="1" strokecmykcolor="0,0,0,100" strokedashes="" strokedashoffset="0" strokejoin="1" strokemiterlimit="4" strokeoverprint="0" strokewidth="0.75" top="-130.69287109375" url="" width="14.3779296875"/><textart artworkknockout="0" blendingmode="0" hidden="0" isisolated="0" left="104.13134765625" locked="0" name="" opacity="100" position="104.13134765625,-24.71533203125" sliced="0" top="-24.71533203125" url="" height="13.02051" width="129.2388" kind="2" wrapped="0" autokerning="-1" baselineshift="0" direction="1" fillcmykcolor="0,0,0,100" fillcolor="1" filled="-1" font="Arial-BoldMT" leading="12" size="10" tracking="0">Engine Room R/B Unit D:</textart><pathitem artworkknockout="0" blendingmode="0" closed="-1" evenodd="0" filled="0" guides="0" height="12.75634765625" hidden="0" isisolated="0" left="138.31982421875" locked="0" name="" note="" opacity="100" anchor="159.95458984375,-87.63671875/149.32470703125,-94.0146484375/138.69482421875,-87.63671875/149.32470703125,-81.25830078125/" leftdirection="159.95458984375,-84.11376953125/155.19580078125,-94.0146484375/138.69482421875,-91.1591796875/143.45458984375,-81.25830078125/" rightdirection="159.95458984375,-91.1591796875/143.45458984375,-94.0146484375/138.69482421875,-84.11376953125/155.19580078125,-81.25830078125/" pointtype="1/1/1/1/" polarity="1" sliced="0" stroked="-1" strokecap="1" strokecolor="2" strokegraycolor="100" strokedashes="" strokedashoffset="0" strokejoin="1" strokemiterlimit="4" strokeoverprint="0" strokewidth="0.75" top="-80.88330078125" url="" width="21.259765625"/><textart artworkknockout="0" blendingmode="0" hidden="0" isisolated="0" left="143.19384765625" locked="0" name="" opacity="100" position="143.19482421875,-81.615234375" sliced="0" top="-81.6142578125" url="" height="12.04297" width="14.45215" kind="2" wrapped="0" autokerning="-1" baselineshift="0" direction="1" fillcmykcolor="0,0,0,100" fillcolor="1" filled="-1" font="ArialMT" leading="12" size="10" tracking="0">1A</textart></layer></indicateinfo><illustinfo id=""><graphic graphicname="A137364.eps" width="" height="" id=""/></illustinfo></tmc-illust>
