<?xml version="1.0" encoding="UTF-8"?>
<tmc-illust ai_version="11.0"><indicateinfo lang="english" name=""><layer artworkknockout="2" blendingmode="0" dimplacedimages="0" isisolated="0" locked="0" name="IndicateLayer" opacity="100" preview="-1" printable="-1" sliced="0" visible="-1"><pathitem artworkknockout="0" blendingmode="0" closed="0" evenodd="0" filled="0" guides="0" height="21.7021484375" hidden="0" isisolated="0" left="160.36669921875" locked="0" name="" note="" opacity="100" anchor="161.86669921875,553.349609375/161.86669921875,575.0517578125/" leftdirection="161.86669921875,553.349609375/161.86669921875,575.0517578125/" rightdirection="161.86669921875,553.349609375/161.86669921875,575.0517578125/" pointtype="2/2/" polarity="1" sliced="0" stroked="-1" strokecap="1" strokecolor="2" strokegraycolor="0" strokedashes="" strokedashoffset="0" strokejoin="1" strokemiterlimit="4" strokeoverprint="0" strokewidth="3" top="575.0517578125" url="" width="0"/><pathitem artworkknockout="0" blendingmode="0" closed="0" evenodd="0" filled="0" guides="0" height="17.34130859375" hidden="0" isisolated="0" left="143.2744140625" locked="0" name="" note="" opacity="100" anchor="144.7744140625,557.71044921875/144.7744140625,575.0517578125/" leftdirection="144.7744140625,557.71044921875/144.7744140625,575.0517578125/" rightdirection="144.7744140625,557.71044921875/144.7744140625,575.0517578125/" pointtype="2/2/" polarity="1" sliced="0" stroked="-1" strokecap="1" strokecolor="2" strokegraycolor="0" strokedashes="" strokedashoffset="0" strokejoin="1" strokemiterlimit="4" strokeoverprint="0" strokewidth="3" top="575.0517578125" url="" width="0"/><pathitem artworkknockout="0" blendingmode="0" closed="0" evenodd="0" filled="0" guides="0" height="17.59814453125" hidden="0" isisolated="0" left="137.3916015625" locked="0" name="" note="" opacity="100" anchor="138.8916015625,557.169921875/138.8916015625,574.76806640625/" leftdirection="138.8916015625,557.169921875/138.8916015625,574.76806640625/" rightdirection="138.8916015625,557.169921875/138.8916015625,574.76806640625/" pointtype="2/2/" polarity="1" sliced="0" stroked="-1" strokecap="1" strokecolor="2" strokegraycolor="0" strokedashes="" strokedashoffset="0" strokejoin="1" strokemiterlimit="4" strokeoverprint="0" strokewidth="3" top="574.76806640625" url="" width="0"/><pathitem artworkknockout="0" blendingmode="0" closed="0" evenodd="0" filled="0" guides="0" height="23.19482421875" hidden="0" isisolated="0" left="133.9521484375" locked="0" name="" note="" opacity="100" anchor="135.4521484375,551.5732421875/135.4521484375,574.76806640625/" leftdirection="135.4521484375,551.5732421875/135.4521484375,574.76806640625/" rightdirection="135.4521484375,551.5732421875/135.4521484375,574.76806640625/" pointtype="2/2/" polarity="1" sliced="0" stroked="-1" strokecap="1" strokecolor="2" strokegraycolor="0" strokedashes="" strokedashoffset="0" strokejoin="1" strokemiterlimit="4" strokeoverprint="0" strokewidth="3" top="574.76806640625" url="" width="0"/><pathitem artworkknockout="0" blendingmode="0" closed="0" evenodd="0" filled="0" guides="0" height="40.64501953125" hidden="0" isisolated="0" left="130.91796875" locked="0" name="" note="" opacity="100" anchor="132.41796875,534.123046875/132.41796875,574.76806640625/" leftdirection="132.41796875,534.123046875/132.41796875,574.76806640625/" rightdirection="132.41796875,534.123046875/132.41796875,574.76806640625/" pointtype="2/2/" polarity="1" sliced="0" stroked="-1" strokecap="1" strokecolor="2" strokegraycolor="0" strokedashes="" strokedashoffset="0" strokejoin="1" strokemiterlimit="4" strokeoverprint="0" strokewidth="3" top="574.76806640625" url="" width="0"/><pathitem artworkknockout="0" blendingmode="0" closed="-1" evenodd="0" filled="-1" fillcolor="1" fillcmykcolor="0,0,0,0" filloverprint="0" guides="0" height="15.857421875" hidden="0" isisolated="0" left="200.900390625" locked="0" name="" note="" opacity="100" anchor="209.26318359375,448.216796875/200.900390625,448.216796875/200.900390625,464.07421875/209.26318359375,464.07421875/" leftdirection="209.26318359375,448.216796875/200.900390625,448.216796875/200.900390625,464.07421875/209.26318359375,464.07421875/" rightdirection="209.26318359375,448.216796875/200.900390625,448.216796875/200.900390625,464.07421875/209.26318359375,464.07421875/" pointtype="2/2/2/2/" polarity="1" sliced="0" stroked="0" top="464.07421875" url="" width="8.36279296875"/><textart artworkknockout="0" blendingmode="0" hidden="0" isisolated="0" left="37.15185546875" locked="0" name="" opacity="100" position="37.15185546875,601.3828125" sliced="0" top="601.3828125" url="" height="10" width="55.40918" kind="2" wrapped="0" autokerning="-1" baselineshift="0" direction="2" fillcmykcolor="0,0,0,100" fillcolor="1" filled="-1" font="Arial-BoldMT" leading="12" size="10" tracking="0">Back Side:</textart><textart artworkknockout="0" blendingmode="0" hidden="0" isisolated="0" left="417.0546875" locked="0" name="" opacity="100" position="417.0703125,516.775390625" sliced="0" top="516.775390625" url="" height="9.5" width="76.10449" kind="2" wrapped="0" autokerning="-1" baselineshift="0" direction="2" fillcmykcolor="0,0,0,100" fillcolor="1" filled="-1" font="ArialMT" leading="12" size="10" tracking="0">Adhesive Center</textart><textart artworkknockout="0" blendingmode="0" hidden="0" isisolated="0" left="406.3681640625" locked="0" name="" opacity="100" position="406.3837890625,576.119140625" sliced="0" top="576.119140625" url="" height="9.935547" width="26.37109" kind="2" wrapped="0" autokerning="-1" baselineshift="0" direction="2" fillcmykcolor="0,0,0,100" fillcolor="1" filled="-1" font="ArialMT" leading="12" size="10" tracking="0">A - A</textart><textart artworkknockout="0" blendingmode="0" hidden="0" isisolated="0" left="406.09765625" locked="0" name="" opacity="100" position="406.09765625,485.97900390625" sliced="0" top="485.97900390625" url="" height="9.935547" width="26.37109" kind="2" wrapped="0" autokerning="-1" baselineshift="0" direction="2" fillcmykcolor="0,0,0,100" fillcolor="1" filled="-1" font="ArialMT" leading="12" size="10" tracking="0">B - B</textart><textart artworkknockout="0" blendingmode="0" hidden="0" isisolated="0" left="405.802734375" locked="0" name="" opacity="100" position="405.802734375,395.544921875" sliced="0" top="395.544921875" url="" height="9.935547" width="26.37109" kind="2" wrapped="0" autokerning="-1" baselineshift="0" direction="2" fillcmykcolor="0,0,0,100" fillcolor="1" filled="-1" font="ArialMT" leading="12" size="10" tracking="0">C - C</textart><textart artworkknockout="0" blendingmode="0" hidden="0" isisolated="0" left="204.61865234375" locked="0" name="" opacity="100" position="204.6337890625,487.20458984375" sliced="0" top="487.20458984375" url="" height="9.935547" width="9.871094" kind="2" wrapped="0" autokerning="-1" baselineshift="0" direction="2" fillcmykcolor="0,0,0,100" fillcolor="1" filled="-1" font="ArialMT" leading="12" size="10" tracking="0">A</textart><textart artworkknockout="0" blendingmode="0" hidden="0" isisolated="0" left="202.02392578125" locked="0" name="" opacity="100" position="202.0390625,462.20458984375" sliced="0" top="462.20458984375" url="" height="9.935547" width="9.871094" kind="2" wrapped="0" autokerning="-1" baselineshift="0" direction="2" fillcmykcolor="0,0,0,100" fillcolor="1" filled="-1" font="ArialMT" leading="12" size="10" tracking="0">A</textart><textart artworkknockout="0" blendingmode="0" hidden="0" isisolated="0" left="204.61865234375" locked="0" name="" opacity="100" position="204.6337890625,487.20458984375" sliced="0" top="487.20458984375" url="" height="9.935547" width="9.871094" kind="2" wrapped="0" autokerning="-1" baselineshift="0" direction="2" fillcmykcolor="0,0,0,100" fillcolor="1" filled="-1" font="ArialMT" leading="12" size="10" tracking="0">A</textart><textart artworkknockout="0" blendingmode="0" hidden="0" isisolated="0" left="133.50341796875" locked="0" name="" opacity="100" position="133.50341796875,457.0048828125" sliced="0" top="457.0048828125" url="" height="10.125" width="8.75" kind="2" wrapped="0" autokerning="-1" baselineshift="0" direction="2" fillcmykcolor="0,0,0,100" fillcolor="1" filled="-1" font="ArialMT" leading="12" size="10" tracking="0">B</textart><textart artworkknockout="0" blendingmode="0" hidden="0" isisolated="0" left="158.50341796875" locked="0" name="" opacity="100" position="158.50341796875,453.5048828125" sliced="0" top="453.5048828125" url="" height="10.125" width="8.75" kind="2" wrapped="0" autokerning="-1" baselineshift="0" direction="2" fillcmykcolor="0,0,0,100" fillcolor="1" filled="-1" font="ArialMT" leading="12" size="10" tracking="0">B</textart><textart artworkknockout="0" blendingmode="0" hidden="0" isisolated="0" left="204.7216796875" locked="0" name="" opacity="100" position="204.7216796875,385.578125" sliced="0" top="385.578125" url="" height="10.125" width="8.75" kind="2" wrapped="0" autokerning="-1" baselineshift="0" direction="2" fillcmykcolor="0,0,0,100" fillcolor="1" filled="-1" font="ArialMT" leading="12" size="10" tracking="0">C</textart><textart artworkknockout="0" blendingmode="0" hidden="0" isisolated="0" left="204.74169921875" locked="0" name="" opacity="100" position="204.74169921875,352.578125" sliced="0" top="352.578125" url="" height="10.125" width="8.75" kind="2" wrapped="0" autokerning="-1" baselineshift="0" direction="2" fillcmykcolor="0,0,0,100" fillcolor="1" filled="-1" font="ArialMT" leading="12" size="10" tracking="0">C</textart><textart artworkknockout="0" blendingmode="0" hidden="0" isisolated="0" left="414.607421875" locked="0" name="" opacity="100" position="414.623046875,426.10986328125" sliced="0" top="426.1103515625" url="" height="9.501465" width="76.10449" kind="2" wrapped="0" autokerning="-1" baselineshift="0" direction="2" fillcmykcolor="0,0,0,100" fillcolor="1" filled="-1" font="ArialMT" leading="12" size="10" tracking="0">Adhesive Center</textart><textart artworkknockout="0" blendingmode="0" hidden="0" isisolated="0" left="438.4052734375" locked="0" name="" opacity="100" position="438.4208984375,338.4462890625" sliced="0" top="338.4462890625" url="" height="9.5" width="76.10449" kind="2" wrapped="0" autokerning="-1" baselineshift="0" direction="2" fillcmykcolor="0,0,0,100" fillcolor="1" filled="-1" font="ArialMT" leading="12" size="10" tracking="0">Adhesive Center</textart><textart artworkknockout="0" blendingmode="0" hidden="0" isisolated="0" left="76.3994140625" locked="0" name="" opacity="100" position="76.3994140625,578.62939453125" sliced="0" top="578.62939453125" url="" height="22.00537" width="38.16943" kind="2" wrapped="0" autokerning="-1" baselineshift="0" direction="2" fillcmykcolor="0,0,0,100" fillcolor="1" filled="-1" font="ArialMT" leading="12" size="10" tracking="0">Ceramic Notch</textart><pathitem artworkknockout="0" blendingmode="0" closed="0" evenodd="0" filled="0" guides="0" height="0" hidden="0" isisolated="0" left="114.56884765625" locked="0" name="" note="" opacity="100" anchor="114.56884765625,573.369140625/161.69677734375,573.369140625/" leftdirection="114.56884765625,573.369140625/161.69677734375,573.369140625/" rightdirection="114.56884765625,573.369140625/161.69677734375,573.369140625/" pointtype="2/2/" polarity="1" sliced="0" stroked="-1" strokecap="1" strokecolor="2" strokegraycolor="100" strokedashes="" strokedashoffset="0" strokejoin="1" strokemiterlimit="4" strokeoverprint="0" strokewidth="0.75" top="573.744140625" url="" width="47.1279296875"/><pathitem artworkknockout="0" blendingmode="0" closed="0" evenodd="0" filled="0" guides="0" height="20.9072265625" hidden="0" isisolated="0" left="161.49169921875" locked="0" name="" note="" opacity="100" anchor="161.86669921875,552.8408203125/161.86669921875,573.748046875/" leftdirection="161.86669921875,552.8408203125/161.86669921875,573.748046875/" rightdirection="161.86669921875,552.8408203125/161.86669921875,573.748046875/" pointtype="2/2/" polarity="1" sliced="0" stroked="-1" strokecap="1" strokecolor="2" strokegraycolor="100" strokedashes="" strokedashoffset="0" strokejoin="1" strokemiterlimit="4" strokeoverprint="0" strokewidth="0.75" top="573.748046875" url="" width="0"/><pathitem artworkknockout="0" blendingmode="0" closed="0" evenodd="0" filled="0" guides="0" height="16.1552734375" hidden="0" isisolated="0" left="144.3994140625" locked="0" name="" note="" opacity="100" anchor="144.7744140625,557.2138671875/144.7744140625,573.369140625/" leftdirection="144.7744140625,557.2138671875/144.7744140625,573.369140625/" rightdirection="144.7744140625,557.2138671875/144.7744140625,573.369140625/" pointtype="2/2/" polarity="1" sliced="0" stroked="-1" strokecap="1" strokecolor="2" strokegraycolor="100" strokedashes="" strokedashoffset="0" strokejoin="1" strokemiterlimit="4" strokeoverprint="0" strokewidth="0.75" top="573.369140625" url="" width="0"/><pathitem artworkknockout="0" blendingmode="0" closed="0" evenodd="0" filled="0" guides="0" height="17.09228515625" hidden="0" isisolated="0" left="138.5166015625" locked="0" name="" note="" opacity="100" anchor="138.8916015625,556.27685546875/138.8916015625,573.369140625/" leftdirection="138.8916015625,556.27685546875/138.8916015625,573.369140625/" rightdirection="138.8916015625,556.27685546875/138.8916015625,573.369140625/" pointtype="2/2/" polarity="1" sliced="0" stroked="-1" strokecap="1" strokecolor="2" strokegraycolor="100" strokedashes="" strokedashoffset="0" strokejoin="1" strokemiterlimit="4" strokeoverprint="0" strokewidth="0.75" top="573.369140625" url="" width="0"/><pathitem artworkknockout="0" blendingmode="0" closed="0" evenodd="0" filled="0" guides="0" height="21.9775390625" hidden="0" isisolated="0" left="135.0771484375" locked="0" name="" note="" opacity="100" anchor="135.4521484375,551.3916015625/135.4521484375,573.369140625/" leftdirection="135.4521484375,551.3916015625/135.4521484375,573.369140625/" rightdirection="135.4521484375,551.3916015625/135.4521484375,573.369140625/" pointtype="2/2/" polarity="1" sliced="0" stroked="-1" strokecap="1" strokecolor="2" strokegraycolor="100" strokedashes="" strokedashoffset="0" strokejoin="1" strokemiterlimit="4" strokeoverprint="0" strokewidth="0.75" top="573.369140625" url="" width="0"/><pathitem artworkknockout="0" blendingmode="0" closed="0" evenodd="0" filled="0" guides="0" height="39.6181640625" hidden="0" isisolated="0" left="132.04296875" locked="0" name="" note="" opacity="100" anchor="132.41796875,534.0341796875/132.41796875,573.65234375/" leftdirection="132.41796875,534.0341796875/132.41796875,573.65234375/" rightdirection="132.41796875,534.0341796875/132.41796875,573.65234375/" pointtype="2/2/" polarity="1" sliced="0" stroked="-1" strokecap="1" strokecolor="2" strokegraycolor="100" strokedashes="" strokedashoffset="0" strokejoin="1" strokemiterlimit="4" strokeoverprint="0" strokewidth="0.75" top="573.65234375" url="" width="0"/><pathitem artworkknockout="0" blendingmode="0" closed="0" evenodd="0" filled="0" guides="0" height="21.7021484375" hidden="0" isisolated="0" left="289.8681640625" locked="0" name="" note="" opacity="100" anchor="291.3681640625,551.91943359375/291.3681640625,573.62158203125/" leftdirection="291.3681640625,551.91943359375/291.3681640625,573.62158203125/" rightdirection="291.3681640625,551.91943359375/291.3681640625,573.62158203125/" pointtype="2/2/" polarity="1" sliced="0" stroked="-1" strokecap="1" strokecolor="2" strokegraycolor="0" strokedashes="" strokedashoffset="0" strokejoin="1" strokemiterlimit="4" strokeoverprint="0" strokewidth="3" top="573.62158203125" url="" width="0"/><pathitem artworkknockout="0" blendingmode="0" closed="0" evenodd="0" filled="0" guides="0" height="17.34130859375" hidden="0" isisolated="0" left="307.2431640625" locked="0" name="" note="" opacity="100" anchor="308.7431640625,555.99658203125/308.7431640625,573.337890625/" leftdirection="308.7431640625,555.99658203125/308.7431640625,573.337890625/" rightdirection="308.7431640625,555.99658203125/308.7431640625,573.337890625/" pointtype="2/2/" polarity="1" sliced="0" stroked="-1" strokecap="1" strokecolor="2" strokegraycolor="0" strokedashes="" strokedashoffset="0" strokejoin="1" strokemiterlimit="4" strokeoverprint="0" strokewidth="3" top="573.337890625" url="" width="0"/><pathitem artworkknockout="0" blendingmode="0" closed="0" evenodd="0" filled="0" guides="0" height="17.59814453125" hidden="0" isisolated="0" left="313.1259765625" locked="0" name="" note="" opacity="100" anchor="314.6259765625,555.73974609375/314.6259765625,573.337890625/" leftdirection="314.6259765625,555.73974609375/314.6259765625,573.337890625/" rightdirection="314.6259765625,555.73974609375/314.6259765625,573.337890625/" pointtype="2/2/" polarity="1" sliced="0" stroked="-1" strokecap="1" strokecolor="2" strokegraycolor="0" strokedashes="" strokedashoffset="0" strokejoin="1" strokemiterlimit="4" strokeoverprint="0" strokewidth="3" top="573.337890625" url="" width="0"/><pathitem artworkknockout="0" blendingmode="0" closed="0" evenodd="0" filled="0" guides="0" height="23.19482421875" hidden="0" isisolated="0" left="316.5654296875" locked="0" name="" note="" opacity="100" anchor="318.0654296875,550.14306640625/318.0654296875,573.337890625/" leftdirection="318.0654296875,550.14306640625/318.0654296875,573.337890625/" rightdirection="318.0654296875,550.14306640625/318.0654296875,573.337890625/" pointtype="2/2/" polarity="1" sliced="0" stroked="-1" strokecap="1" strokecolor="2" strokegraycolor="0" strokedashes="" strokedashoffset="0" strokejoin="1" strokemiterlimit="4" strokeoverprint="0" strokewidth="3" top="573.337890625" url="" width="0"/><pathitem artworkknockout="0" blendingmode="0" closed="0" evenodd="0" filled="0" guides="0" height="40.64501953125" hidden="0" isisolated="0" left="319.599609375" locked="0" name="" note="" opacity="100" anchor="321.099609375,532.69287109375/321.099609375,573.337890625/" leftdirection="321.099609375,532.69287109375/321.099609375,573.337890625/" rightdirection="321.099609375,532.69287109375/321.099609375,573.337890625/" pointtype="2/2/" polarity="1" sliced="0" stroked="-1" strokecap="1" strokecolor="2" strokegraycolor="0" strokedashes="" strokedashoffset="0" strokejoin="1" strokemiterlimit="4" strokeoverprint="0" strokewidth="3" top="573.337890625" url="" width="0"/><textart artworkknockout="0" blendingmode="0" hidden="0" isisolated="0" left="340.1201171875" locked="0" name="" opacity="100" position="340.1201171875,577.1240234375" sliced="0" top="577.1240234375" url="" height="22.00537" width="38.16895" kind="2" wrapped="0" autokerning="-1" baselineshift="0" direction="2" fillcmykcolor="0,0,0,100" fillcolor="1" filled="-1" font="ArialMT" leading="12" size="10" tracking="0">Ceramic Notch</textart><pathitem artworkknockout="0" blendingmode="0" closed="0" evenodd="0" filled="0" guides="0" height="0" hidden="0" isisolated="0" left="291" locked="0" name="" note="" opacity="100" anchor="338.94921875,571.93896484375/291,571.93896484375/" leftdirection="338.94921875,571.93896484375/291,571.93896484375/" rightdirection="338.94921875,571.93896484375/291,571.93896484375/" pointtype="2/2/" polarity="1" sliced="0" stroked="-1" strokecap="1" strokecolor="2" strokegraycolor="100" strokedashes="" strokedashoffset="0" strokejoin="1" strokemiterlimit="4" strokeoverprint="0" strokewidth="0.75" top="572.31396484375" url="" width="47.94921875"/><pathitem artworkknockout="0" blendingmode="0" closed="0" evenodd="0" filled="0" guides="0" height="20.5283203125" hidden="0" isisolated="0" left="290.9931640625" locked="0" name="" note="" opacity="100" anchor="291.3681640625,551.41064453125/291.3681640625,571.93896484375/" leftdirection="291.3681640625,551.41064453125/291.3681640625,571.93896484375/" rightdirection="291.3681640625,551.41064453125/291.3681640625,571.93896484375/" pointtype="2/2/" polarity="1" sliced="0" stroked="-1" strokecap="1" strokecolor="2" strokegraycolor="100" strokedashes="" strokedashoffset="0" strokejoin="1" strokemiterlimit="4" strokeoverprint="0" strokewidth="0.75" top="571.93896484375" url="" width="0"/><pathitem artworkknockout="0" blendingmode="0" closed="0" evenodd="0" filled="0" guides="0" height="16.1552734375" hidden="0" isisolated="0" left="308.3681640625" locked="0" name="" note="" opacity="100" anchor="308.7431640625,555.78369140625/308.7431640625,571.93896484375/" leftdirection="308.7431640625,555.78369140625/308.7431640625,571.93896484375/" rightdirection="308.7431640625,555.78369140625/308.7431640625,571.93896484375/" pointtype="2/2/" polarity="1" sliced="0" stroked="-1" strokecap="1" strokecolor="2" strokegraycolor="100" strokedashes="" strokedashoffset="0" strokejoin="1" strokemiterlimit="4" strokeoverprint="0" strokewidth="0.75" top="571.93896484375" url="" width="0"/><pathitem artworkknockout="0" blendingmode="0" closed="0" evenodd="0" filled="0" guides="0" height="17.09228515625" hidden="0" isisolated="0" left="314.2509765625" locked="0" name="" note="" opacity="100" anchor="314.6259765625,554.8466796875/314.6259765625,571.93896484375/" leftdirection="314.6259765625,554.8466796875/314.6259765625,571.93896484375/" rightdirection="314.6259765625,554.8466796875/314.6259765625,571.93896484375/" pointtype="2/2/" polarity="1" sliced="0" stroked="-1" strokecap="1" strokecolor="2" strokegraycolor="100" strokedashes="" strokedashoffset="0" strokejoin="1" strokemiterlimit="4" strokeoverprint="0" strokewidth="0.75" top="571.93896484375" url="" width="0"/><pathitem artworkknockout="0" blendingmode="0" closed="0" evenodd="0" filled="0" guides="0" height="21.9775390625" hidden="0" isisolated="0" left="317.6904296875" locked="0" name="" note="" opacity="100" anchor="318.0654296875,549.96142578125/318.0654296875,571.93896484375/" leftdirection="318.0654296875,549.96142578125/318.0654296875,571.93896484375/" rightdirection="318.0654296875,549.96142578125/318.0654296875,571.93896484375/" pointtype="2/2/" polarity="1" sliced="0" stroked="-1" strokecap="1" strokecolor="2" strokegraycolor="100" strokedashes="" strokedashoffset="0" strokejoin="1" strokemiterlimit="4" strokeoverprint="0" strokewidth="0.75" top="571.93896484375" url="" width="0"/><pathitem artworkknockout="0" blendingmode="0" closed="0" evenodd="0" filled="0" guides="0" height="39.6181640625" hidden="0" isisolated="0" left="320.724609375" locked="0" name="" note="" opacity="100" anchor="321.099609375,532.60400390625/321.099609375,572.22216796875/" leftdirection="321.099609375,532.60400390625/321.099609375,572.22216796875/" rightdirection="321.099609375,532.60400390625/321.099609375,572.22216796875/" pointtype="2/2/" polarity="1" sliced="0" stroked="-1" strokecap="1" strokecolor="2" strokegraycolor="100" strokedashes="" strokedashoffset="0" strokejoin="1" strokemiterlimit="4" strokeoverprint="0" strokewidth="0.75" top="572.22216796875" url="" width="0"/><textart artworkknockout="0" blendingmode="0" hidden="0" isisolated="0" left="66.59521484375" locked="0" name="" opacity="100" position="66.59521484375,328.3291015625" sliced="0" top="328.3291015625" url="" height="22.00586" width="38.16943" kind="2" wrapped="0" autokerning="-1" baselineshift="0" direction="2" fillcmykcolor="0,0,0,100" fillcolor="1" filled="-1" font="ArialMT" leading="12" size="10" tracking="0">Ceramic Notch</textart><textart artworkknockout="0" blendingmode="0" hidden="0" isisolated="0" left="354.720703125" locked="0" name="" opacity="100" position="354.720703125,325.2041015625" sliced="0" top="325.2041015625" url="" height="22.00586" width="38.16895" kind="2" wrapped="0" autokerning="-1" baselineshift="0" direction="2" fillcmykcolor="0,0,0,100" fillcolor="1" filled="-1" font="ArialMT" leading="12" size="10" tracking="0">Ceramic Notch</textart><pathitem artworkknockout="0" blendingmode="0" closed="0" evenodd="0" filled="0" guides="0" height="35.771484375" hidden="0" isisolated="0" left="439.1572265625" locked="0" name="" note="" opacity="100" anchor="440.1572265625,533.06201171875/440.1572265625,568.83349609375/" leftdirection="440.1572265625,533.06201171875/440.1572265625,568.83349609375/" rightdirection="440.1572265625,533.06201171875/440.1572265625,568.83349609375/" pointtype="2/2/" polarity="1" sliced="0" stroked="-1" strokecap="1" strokecolor="2" strokegraycolor="0" strokedashes="" strokedashoffset="0" strokejoin="1" strokemiterlimit="4" strokeoverprint="0" strokewidth="2" top="568.83349609375" url="" width="0"/><pathitem artworkknockout="0" blendingmode="0" closed="0" evenodd="0" filled="0" guides="0" height="23.97021484375" hidden="0" isisolated="0" left="439.7822265625" locked="0" name="" note="" opacity="100" anchor="440.1572265625,531.86328125/440.1572265625,555.83349609375/" leftdirection="440.1572265625,531.86328125/440.1572265625,555.83349609375/" rightdirection="440.1572265625,531.86328125/440.1572265625,555.83349609375/" pointtype="2/2/" polarity="1" sliced="0" stroked="-1" strokecap="1" strokecolor="2" strokegraycolor="100" strokedashes="" strokedashoffset="0" strokejoin="1" strokemiterlimit="4" strokeoverprint="0" strokewidth="0.75" top="555.83349609375" url="" width="0"/><pathitem artworkknockout="0" blendingmode="0" closed="0" evenodd="0" filled="0" guides="0" height="28.91650390625" hidden="0" isisolated="0" left="454.599609375" locked="0" name="" note="" opacity="100" anchor="454.974609375,535.1669921875/454.974609375,564.08349609375/" leftdirection="454.974609375,535.1669921875/454.974609375,564.08349609375/" rightdirection="454.974609375,535.1669921875/454.974609375,564.08349609375/" pointtype="2/2/" polarity="1" sliced="0" stroked="-1" strokecap="1" strokecolor="2" strokegraycolor="100" strokedashes="" strokedashoffset="0" strokejoin="1" strokemiterlimit="4" strokeoverprint="0" strokewidth="0.75" top="564.08349609375" url="" width="0"/><pathitem artworkknockout="0" blendingmode="0" closed="0" evenodd="0" filled="0" guides="0" height="28.91650390625" hidden="0" isisolated="0" left="462.5439453125" locked="0" name="" note="" opacity="100" anchor="462.9189453125,535.1669921875/462.9189453125,564.08349609375/" leftdirection="462.9189453125,535.1669921875/462.9189453125,564.08349609375/" rightdirection="462.9189453125,535.1669921875/462.9189453125,564.08349609375/" pointtype="2/2/" polarity="1" sliced="0" stroked="-1" strokecap="1" strokecolor="2" strokegraycolor="100" strokedashes="" strokedashoffset="0" strokejoin="1" strokemiterlimit="4" strokeoverprint="0" strokewidth="0.75" top="564.08349609375" url="" width="0"/><pathitem artworkknockout="0" blendingmode="0" closed="0" evenodd="0" filled="0" guides="0" height="0" hidden="0" isisolated="0" left="443.708984375" locked="0" name="" note="" opacity="100" anchor="443.708984375,560.8955078125/474.66015625,560.8955078125/" leftdirection="443.708984375,560.8955078125/474.66015625,560.8955078125/" rightdirection="443.708984375,560.8955078125/474.66015625,560.8955078125/" pointtype="1/2/" polarity="1" sliced="0" stroked="-1" strokecap="1" strokecolor="1" strokecmykcolor="0,0,0,100" strokedashes="" strokedashoffset="0" strokejoin="1" strokemiterlimit="4" strokeoverprint="0" strokewidth="0.75" top="561.2705078125" url="" width="30.951171875"/><pathitem artworkknockout="0" blendingmode="0" closed="-1" evenodd="0" filled="-1" fillcolor="1" fillcmykcolor="0,0,0,100" filloverprint="0" guides="0" height="3.673828125" hidden="0" isisolated="0" left="448.701171875" locked="0" name="" note="" opacity="100" anchor="448.701171875,559.052734375/455.177734375,560.8896484375/448.701171875,562.7265625/" leftdirection="448.701171875,559.052734375/455.177734375,560.8896484375/448.701171875,562.7265625/" rightdirection="448.701171875,559.052734375/455.177734375,560.8896484375/448.701171875,562.7265625/" pointtype="1/1/1/" polarity="-1" sliced="0" stroked="0" top="562.7265625" url="" width="6.4765625"/><pathitem artworkknockout="0" blendingmode="0" closed="-1" evenodd="0" filled="-1" fillcolor="1" fillcmykcolor="0,0,0,100" filloverprint="0" guides="0" height="3.673828125" hidden="0" isisolated="0" left="462.5048828125" locked="0" name="" note="" opacity="100" anchor="468.9814453125,562.73828125/462.5048828125,560.9013671875/468.9814453125,559.064453125/" leftdirection="468.9814453125,562.73828125/462.5048828125,560.9013671875/468.9814453125,559.064453125/" rightdirection="468.9814453125,562.73828125/462.5048828125,560.9013671875/468.9814453125,559.064453125/" pointtype="1/1/1/" polarity="-1" sliced="0" stroked="0" top="562.73828125" url="" width="6.4765625"/><pathitem artworkknockout="0" blendingmode="0" closed="0" evenodd="0" filled="0" guides="0" height="0" hidden="0" isisolated="0" left="426.833984375" locked="0" name="" note="" opacity="100" anchor="461.5009765625,552.08349609375/426.833984375,552.08349609375/" leftdirection="461.5009765625,552.08349609375/426.833984375,552.08349609375/" rightdirection="461.5009765625,552.08349609375/426.833984375,552.08349609375/" pointtype="1/2/" polarity="1" sliced="0" stroked="-1" strokecap="1" strokecolor="1" strokecmykcolor="0,0,0,100" strokedashes="" strokedashoffset="0" strokejoin="1" strokemiterlimit="4" strokeoverprint="0" strokewidth="0.75" top="552.45849609375" url="" width="34.6669921875"/><pathitem artworkknockout="0" blendingmode="0" closed="-1" evenodd="0" filled="-1" fillcolor="1" fillcmykcolor="0,0,0,100" filloverprint="0" guides="0" height="3.673828125" hidden="0" isisolated="0" left="454.1279296875" locked="0" name="" note="" opacity="100" anchor="460.6044921875,550.24072265625/454.1279296875,552.07763671875/460.6044921875,553.91455078125/" leftdirection="460.6044921875,550.24072265625/454.1279296875,552.07763671875/460.6044921875,553.91455078125/" rightdirection="460.6044921875,550.24072265625/454.1279296875,552.07763671875/460.6044921875,553.91455078125/" pointtype="1/1/1/" polarity="1" sliced="0" stroked="0" top="553.91455078125" url="" width="6.4765625"/><pathitem artworkknockout="0" blendingmode="0" closed="-1" evenodd="0" filled="-1" fillcolor="1" fillcmykcolor="0,0,0,100" filloverprint="0" guides="0" height="3.673828125" hidden="0" isisolated="0" left="433.1982421875" locked="0" name="" note="" opacity="100" anchor="433.1982421875,553.92626953125/439.6748046875,552.08935546875/433.1982421875,550.25244140625/" leftdirection="433.1982421875,553.92626953125/439.6748046875,552.08935546875/433.1982421875,550.25244140625/" rightdirection="433.1982421875,553.92626953125/439.6748046875,552.08935546875/433.1982421875,550.25244140625/" pointtype="1/1/1/" polarity="1" sliced="0" stroked="0" top="553.92626953125" url="" width="6.4765625"/><textart artworkknockout="0" blendingmode="0" hidden="0" isisolated="0" left="419.0498046875" locked="0" name="" opacity="100" position="419.0498046875,557.18798828125" sliced="0" top="557.18798828125" url="" height="9.083008" width="6.583984" kind="2" wrapped="0" autokerning="-1" baselineshift="0" direction="2" fillcmykcolor="0,0,0,100" fillcolor="1" filled="-1" font="ArialMT" leading="12" size="10" tracking="0">a</textart><textart artworkknockout="0" blendingmode="0" hidden="0" isisolated="0" left="476.3212890625" locked="0" name="" opacity="100" position="476.3212890625,566.69189453125" sliced="0" top="566.69189453125" url="" height="10.95801" width="6.625" kind="2" wrapped="0" autokerning="-1" baselineshift="0" direction="2" fillcmykcolor="0,0,0,100" fillcolor="1" filled="-1" font="ArialMT" leading="12" size="10" tracking="0">b</textart><pathitem artworkknockout="0" blendingmode="0" closed="0" evenodd="0" filled="0" guides="0" height="35.771484375" hidden="0" isisolated="0" left="437.7568359375" locked="0" name="" note="" opacity="100" anchor="438.7568359375,442.63427734375/438.7568359375,478.40576171875/" leftdirection="438.7568359375,442.63427734375/438.7568359375,478.40576171875/" rightdirection="438.7568359375,442.63427734375/438.7568359375,478.40576171875/" pointtype="2/2/" polarity="1" sliced="0" stroked="-1" strokecap="1" strokecolor="2" strokegraycolor="0" strokedashes="" strokedashoffset="0" strokejoin="1" strokemiterlimit="4" strokeoverprint="0" strokewidth="2" top="478.40576171875" url="" width="0"/><pathitem artworkknockout="0" blendingmode="0" closed="0" evenodd="0" filled="0" guides="0" height="24.99853515625" hidden="0" isisolated="0" left="438.3818359375" locked="0" name="" note="" opacity="100" anchor="438.7568359375,441.435546875/438.7568359375,466.43408203125/" leftdirection="438.7568359375,441.435546875/438.7568359375,466.43408203125/" rightdirection="438.7568359375,441.435546875/438.7568359375,466.43408203125/" pointtype="2/2/" polarity="1" sliced="0" stroked="-1" strokecap="1" strokecolor="2" strokegraycolor="100" strokedashes="" strokedashoffset="0" strokejoin="1" strokemiterlimit="4" strokeoverprint="0" strokewidth="0.75" top="466.43408203125" url="" width="0"/><pathitem artworkknockout="0" blendingmode="0" closed="0" evenodd="0" filled="0" guides="0" height="30.44482421875" hidden="0" isisolated="0" left="460.0107421875" locked="0" name="" note="" opacity="100" anchor="460.3857421875,444.7392578125/460.3857421875,475.18408203125/" leftdirection="460.3857421875,444.7392578125/460.3857421875,475.18408203125/" rightdirection="460.3857421875,444.7392578125/460.3857421875,475.18408203125/" pointtype="2/2/" polarity="1" sliced="0" stroked="-1" strokecap="1" strokecolor="2" strokegraycolor="100" strokedashes="" strokedashoffset="0" strokejoin="1" strokemiterlimit="4" strokeoverprint="0" strokewidth="0.75" top="475.18408203125" url="" width="0"/><pathitem artworkknockout="0" blendingmode="0" closed="0" evenodd="0" filled="0" guides="0" height="0" hidden="0" isisolated="0" left="441.625" locked="0" name="" note="" opacity="100" anchor="441.625,472.169921875/472.8349609375,472.169921875/" leftdirection="441.625,472.169921875/472.8349609375,472.169921875/" rightdirection="441.625,472.169921875/472.8349609375,472.169921875/" pointtype="1/2/" polarity="1" sliced="0" stroked="-1" strokecap="1" strokecolor="1" strokecmykcolor="0,0,0,100" strokedashes="" strokedashoffset="0" strokejoin="1" strokemiterlimit="4" strokeoverprint="0" strokewidth="0.75" top="472.544921875" url="" width="31.2099609375"/><pathitem artworkknockout="0" blendingmode="0" closed="-1" evenodd="0" filled="-1" fillcolor="1" fillcmykcolor="0,0,0,100" filloverprint="0" guides="0" height="3.673828125" hidden="0" isisolated="0" left="445.6015625" locked="0" name="" note="" opacity="100" anchor="445.6015625,470.3271484375/452.078125,472.1640625/445.6015625,474.0009765625/" leftdirection="445.6015625,470.3271484375/452.078125,472.1640625/445.6015625,474.0009765625/" rightdirection="445.6015625,470.3271484375/452.078125,472.1640625/445.6015625,474.0009765625/" pointtype="1/1/1/" polarity="-1" sliced="0" stroked="0" top="474.0009765625" url="" width="6.4765625"/><pathitem artworkknockout="0" blendingmode="0" closed="-1" evenodd="0" filled="-1" fillcolor="1" fillcmykcolor="0,0,0,100" filloverprint="0" guides="0" height="3.673828125" hidden="0" isisolated="0" left="460.5380859375" locked="0" name="" note="" opacity="100" anchor="467.0146484375,474.0126953125/460.5380859375,472.17578125/467.0146484375,470.3388671875/" leftdirection="467.0146484375,474.0126953125/460.5380859375,472.17578125/467.0146484375,470.3388671875/" rightdirection="467.0146484375,474.0126953125/460.5380859375,472.17578125/467.0146484375,470.3388671875/" pointtype="1/1/1/" polarity="-1" sliced="0" stroked="0" top="474.0126953125" url="" width="6.4765625"/><textart artworkknockout="0" blendingmode="0" hidden="0" isisolated="0" left="501.4130859375" locked="0" name="" opacity="100" position="501.4130859375,391.0263671875" sliced="0" top="391.0263671875" url="" height="10.95703" width="6.625" kind="2" wrapped="0" autokerning="-1" baselineshift="0" direction="2" fillcmykcolor="0,0,0,100" fillcolor="1" filled="-1" font="ArialMT" leading="12" size="10" tracking="0">c</textart><pathitem artworkknockout="0" blendingmode="0" closed="0" evenodd="0" filled="0" guides="0" height="31.51806640625" hidden="0" isisolated="0" left="451.765625" locked="0" name="" note="" opacity="100" anchor="452.140625,443.666015625/452.140625,475.18408203125/" leftdirection="452.140625,443.666015625/452.140625,475.18408203125/" rightdirection="452.140625,443.666015625/452.140625,475.18408203125/" pointtype="2/2/" polarity="1" sliced="0" stroked="-1" strokecap="1" strokecolor="2" strokegraycolor="100" strokedashes="" strokedashoffset="0" strokejoin="1" strokemiterlimit="4" strokeoverprint="0" strokewidth="0.75" top="475.18408203125" url="" width="0"/><pathitem artworkknockout="0" blendingmode="0" closed="0" evenodd="0" filled="0" guides="0" height="0" hidden="0" isisolated="0" left="424.283203125" locked="0" name="" note="" opacity="100" anchor="459.533203125,462.18408203125/424.283203125,462.18408203125/" leftdirection="459.533203125,462.18408203125/424.283203125,462.18408203125/" rightdirection="459.533203125,462.18408203125/424.283203125,462.18408203125/" pointtype="1/2/" polarity="1" sliced="0" stroked="-1" strokecap="1" strokecolor="1" strokecmykcolor="0,0,0,100" strokedashes="" strokedashoffset="0" strokejoin="1" strokemiterlimit="4" strokeoverprint="0" strokewidth="0.75" top="462.55908203125" url="" width="35.25"/><pathitem artworkknockout="0" blendingmode="0" closed="-1" evenodd="0" filled="-1" fillcolor="1" fillcmykcolor="0,0,0,100" filloverprint="0" guides="0" height="3.673828125" hidden="0" isisolated="0" left="452.1435546875" locked="0" name="" note="" opacity="100" anchor="458.6201171875,460.34130859375/452.1435546875,462.17822265625/458.6201171875,464.01513671875/" leftdirection="458.6201171875,460.34130859375/452.1435546875,462.17822265625/458.6201171875,464.01513671875/" rightdirection="458.6201171875,460.34130859375/452.1435546875,462.17822265625/458.6201171875,464.01513671875/" pointtype="1/1/1/" polarity="1" sliced="0" stroked="0" top="464.01513671875" url="" width="6.4765625"/><pathitem artworkknockout="0" blendingmode="0" closed="-1" evenodd="0" filled="-1" fillcolor="1" fillcmykcolor="0,0,0,100" filloverprint="0" guides="0" height="3.673828125" hidden="0" isisolated="0" left="432.162109375" locked="0" name="" note="" opacity="100" anchor="432.162109375,464.02685546875/438.638671875,462.18994140625/432.162109375,460.35302734375/" leftdirection="432.162109375,464.02685546875/438.638671875,462.18994140625/432.162109375,460.35302734375/" rightdirection="432.162109375,464.02685546875/438.638671875,462.18994140625/432.162109375,460.35302734375/" pointtype="1/1/1/" polarity="1" sliced="0" stroked="0" top="464.02685546875" url="" width="6.4765625"/><pathitem artworkknockout="0" blendingmode="0" closed="0" evenodd="0" filled="0" guides="0" height="35.771484375" hidden="0" isisolated="0" left="487.8232421875" locked="0" name="" note="" opacity="100" anchor="488.8232421875,354.486328125/488.8232421875,390.2578125/" leftdirection="488.8232421875,354.486328125/488.8232421875,390.2578125/" rightdirection="488.8232421875,354.486328125/488.8232421875,390.2578125/" pointtype="2/2/" polarity="1" sliced="0" stroked="-1" strokecap="1" strokecolor="2" strokegraycolor="0" strokedashes="" strokedashoffset="0" strokejoin="1" strokemiterlimit="4" strokeoverprint="0" strokewidth="2" top="390.2578125" url="" width="0"/><pathitem artworkknockout="0" blendingmode="0" closed="0" evenodd="0" filled="0" guides="0" height="36.13671875" hidden="0" isisolated="0" left="488.4482421875" locked="0" name="" note="" opacity="100" anchor="488.8232421875,353.2880859375/488.8232421875,389.4248046875/" leftdirection="488.8232421875,353.2880859375/488.8232421875,389.4248046875/" rightdirection="488.8232421875,353.2880859375/488.8232421875,389.4248046875/" pointtype="2/2/" polarity="1" sliced="0" stroked="-1" strokecap="1" strokecolor="2" strokegraycolor="100" strokedashes="" strokedashoffset="0" strokejoin="1" strokemiterlimit="4" strokeoverprint="0" strokewidth="0.75" top="389.4248046875" url="" width="0"/><pathitem artworkknockout="0" blendingmode="0" closed="0" evenodd="0" filled="0" guides="0" height="34.025390625" hidden="0" isisolated="0" left="476.234375" locked="0" name="" note="" opacity="100" anchor="476.609375,354.6328125/476.609375,388.658203125/" leftdirection="476.609375,354.6328125/476.609375,388.658203125/" rightdirection="476.609375,354.6328125/476.609375,388.658203125/" pointtype="2/2/" polarity="1" sliced="0" stroked="-1" strokecap="1" strokecolor="2" strokegraycolor="100" strokedashes="" strokedashoffset="0" strokejoin="1" strokemiterlimit="4" strokeoverprint="0" strokewidth="0.75" top="388.658203125" url="" width="0"/><pathitem artworkknockout="0" blendingmode="0" closed="0" evenodd="0" filled="0" guides="0" height="0" hidden="0" isisolated="0" left="464.5986328125" locked="0" name="" note="" opacity="100" anchor="464.5986328125,385.158203125/499.7919921875,385.158203125/" leftdirection="464.5986328125,385.158203125/499.7919921875,385.158203125/" rightdirection="464.5986328125,385.158203125/499.7919921875,385.158203125/" pointtype="1/2/" polarity="1" sliced="0" stroked="-1" strokecap="1" strokecolor="1" strokecmykcolor="0,0,0,100" strokedashes="" strokedashoffset="0" strokejoin="1" strokemiterlimit="4" strokeoverprint="0" strokewidth="0.75" top="385.533203125" url="" width="35.193359375"/><pathitem artworkknockout="0" blendingmode="0" closed="-1" evenodd="0" filled="-1" fillcolor="1" fillcmykcolor="0,0,0,100" filloverprint="0" guides="0" height="3.673828125" hidden="0" isisolated="0" left="470.3212890625" locked="0" name="" note="" opacity="100" anchor="470.3212890625,383.3154296875/476.7978515625,385.15234375/470.3212890625,386.9892578125/" leftdirection="470.3212890625,383.3154296875/476.7978515625,385.15234375/470.3212890625,386.9892578125/" rightdirection="470.3212890625,383.3154296875/476.7978515625,385.15234375/470.3212890625,386.9892578125/" pointtype="1/1/1/" polarity="-1" sliced="0" stroked="0" top="386.9892578125" url="" width="6.4765625"/><pathitem artworkknockout="0" blendingmode="0" closed="-1" evenodd="0" filled="-1" fillcolor="1" fillcmykcolor="0,0,0,100" filloverprint="0" guides="0" height="3.673828125" hidden="0" isisolated="0" left="488.8388671875" locked="0" name="" note="" opacity="100" anchor="495.3154296875,387.0087890625/488.8388671875,385.171875/495.3154296875,383.3349609375/" leftdirection="495.3154296875,387.0087890625/488.8388671875,385.171875/495.3154296875,383.3349609375/" rightdirection="495.3154296875,387.0087890625/488.8388671875,385.171875/495.3154296875,383.3349609375/" pointtype="1/1/1/" polarity="-1" sliced="0" stroked="0" top="387.0087890625" url="" width="6.4765625"/><pathitem artworkknockout="0" blendingmode="0" closed="0" evenodd="0" filled="0" guides="0" height="19.521484375" hidden="0" isisolated="0" left="458.501953125" locked="0" name="" note="" opacity="100" anchor="458.876953125,356.12890625/458.876953125,375.650390625/" leftdirection="458.876953125,356.12890625/458.876953125,375.650390625/" rightdirection="458.876953125,356.12890625/458.876953125,375.650390625/" pointtype="2/2/" polarity="1" sliced="0" stroked="-1" strokecap="1" strokecolor="2" strokegraycolor="100" strokedashes="" strokedashoffset="0" strokejoin="1" strokemiterlimit="4" strokeoverprint="0" strokewidth="0.75" top="375.650390625" url="" width="0"/><pathitem artworkknockout="0" blendingmode="0" closed="0" evenodd="0" filled="0" guides="0" height="0" hidden="0" isisolated="0" left="447.7919921875" locked="0" name="" note="" opacity="100" anchor="486.2919921875,370.212890625/447.7919921875,370.212890625/" leftdirection="486.2919921875,370.212890625/447.7919921875,370.212890625/" rightdirection="486.2919921875,370.212890625/447.7919921875,370.212890625/" pointtype="1/2/" polarity="1" sliced="0" stroked="-1" strokecap="1" strokecolor="1" strokecmykcolor="0,0,0,100" strokedashes="" strokedashoffset="0" strokejoin="1" strokemiterlimit="4" strokeoverprint="0" strokewidth="0.75" top="370.587890625" url="" width="38.5"/><pathitem artworkknockout="0" blendingmode="0" closed="-1" evenodd="0" filled="-1" fillcolor="1" fillcmykcolor="0,0,0,100" filloverprint="0" guides="0" height="3.673828125" hidden="0" isisolated="0" left="476.927734375" locked="0" name="" note="" opacity="100" anchor="483.404296875,368.3701171875/476.927734375,370.20703125/483.404296875,372.0439453125/" leftdirection="483.404296875,368.3701171875/476.927734375,370.20703125/483.404296875,372.0439453125/" rightdirection="483.404296875,368.3701171875/476.927734375,370.20703125/483.404296875,372.0439453125/" pointtype="1/1/1/" polarity="1" sliced="0" stroked="0" top="372.0439453125" url="" width="6.4765625"/><pathitem artworkknockout="0" blendingmode="0" closed="-1" evenodd="0" filled="-1" fillcolor="1" fillcmykcolor="0,0,0,100" filloverprint="0" guides="0" height="3.673828125" hidden="0" isisolated="0" left="452.2861328125" locked="0" name="" note="" opacity="100" anchor="452.2861328125,372.0556640625/458.7626953125,370.21875/452.2861328125,368.3818359375/" leftdirection="452.2861328125,372.0556640625/458.7626953125,370.21875/452.2861328125,368.3818359375/" rightdirection="452.2861328125,372.0556640625/458.7626953125,370.21875/452.2861328125,368.3818359375/" pointtype="1/1/1/" polarity="1" sliced="0" stroked="0" top="372.0556640625" url="" width="6.4765625"/><textart artworkknockout="0" blendingmode="0" hidden="0" isisolated="0" left="417.1669921875" locked="0" name="" opacity="100" position="417.1669921875,467.88037109375" sliced="0" top="467.88037109375" url="" height="9.083008" width="6.583984" kind="2" wrapped="0" autokerning="-1" baselineshift="0" direction="2" fillcmykcolor="0,0,0,100" fillcolor="1" filled="-1" font="ArialMT" leading="12" size="10" tracking="0">a</textart><textart artworkknockout="0" blendingmode="0" hidden="0" isisolated="0" left="473.9052734375" locked="0" name="" opacity="100" position="473.9052734375,476.55810546875" sliced="0" top="476.55810546875" url="" height="10.95801" width="6.625" kind="2" wrapped="0" autokerning="-1" baselineshift="0" direction="2" fillcmykcolor="0,0,0,100" fillcolor="1" filled="-1" font="ArialMT" leading="12" size="10" tracking="0">b</textart><textart artworkknockout="0" blendingmode="0" hidden="0" isisolated="0" left="440.5390625" locked="0" name="" opacity="100" position="440.5390625,375.525390625" sliced="0" top="375.525390625" url="" height="10.95801" width="6.625" kind="2" wrapped="0" autokerning="-1" baselineshift="0" direction="2" fillcmykcolor="0,0,0,100" fillcolor="1" filled="-1" font="ArialMT" leading="12" size="10" tracking="0">b</textart><pathitem artworkknockout="0" blendingmode="0" closed="0" evenodd="0" filled="0" guides="0" height="0" hidden="0" isisolated="0" left="317.8271484375" locked="0" name="" note="" opacity="100" anchor="317.8271484375,316.58984375/354.720703125,316.58984375/" leftdirection="317.8271484375,316.58984375/354.720703125,316.58984375/" rightdirection="317.8271484375,316.58984375/354.720703125,316.58984375/" pointtype="2/2/" polarity="1" sliced="0" stroked="-1" strokecap="1" strokecolor="1" strokecmykcolor="0,0,0,0" strokedashes="" strokedashoffset="0" strokejoin="1" strokemiterlimit="4" strokeoverprint="0" strokewidth="3" top="318.08984375" url="" width="36.8935546875"/><pathitem artworkknockout="0" blendingmode="0" closed="0" evenodd="0" filled="0" guides="0" height="0" hidden="0" isisolated="0" left="310.9755859375" locked="0" name="" note="" opacity="100" anchor="310.9755859375,299.9921875/348.8076171875,299.9921875/" leftdirection="310.9755859375,299.9921875/348.8076171875,299.9921875/" rightdirection="310.9755859375,299.9921875/348.8076171875,299.9921875/" pointtype="2/2/" polarity="1" sliced="0" stroked="-1" strokecap="1" strokecolor="1" strokecmykcolor="0,0,0,0" strokedashes="" strokedashoffset="0" strokejoin="1" strokemiterlimit="4" strokeoverprint="0" strokewidth="3" top="301.4921875" url="" width="37.83203125"/><pathitem artworkknockout="0" blendingmode="0" closed="0" evenodd="0" filled="0" guides="0" height="0" hidden="0" isisolated="0" left="316.5869140625" locked="0" name="" note="" opacity="100" anchor="316.5869140625,307.560546875/348.8076171875,307.560546875/" leftdirection="316.5869140625,307.560546875/348.8076171875,307.560546875/" rightdirection="316.5869140625,307.560546875/348.8076171875,307.560546875/" pointtype="2/2/" polarity="1" sliced="0" stroked="-1" strokecap="1" strokecolor="1" strokecmykcolor="0,0,0,0" strokedashes="" strokedashoffset="0" strokejoin="1" strokemiterlimit="4" strokeoverprint="0" strokewidth="3" top="309.060546875" url="" width="32.220703125"/><pathitem artworkknockout="0" blendingmode="0" closed="0" evenodd="0" filled="0" guides="0" height="0" hidden="0" isisolated="0" left="317.0478515625" locked="0" name="" note="" opacity="100" anchor="317.0478515625,316.58984375/352.833984375,316.58984375/" leftdirection="317.0478515625,316.58984375/352.833984375,316.58984375/" rightdirection="317.0478515625,316.58984375/352.833984375,316.58984375/" pointtype="2/2/" polarity="1" sliced="0" stroked="-1" strokecap="1" strokecolor="1" strokecmykcolor="0,0,0,100" strokedashes="" strokedashoffset="0" strokejoin="1" strokemiterlimit="4" strokeoverprint="0" strokewidth="0.75" top="316.96484375" url="" width="35.7861328125"/><pathitem artworkknockout="0" blendingmode="0" closed="0" evenodd="0" filled="0" guides="0" height="0" hidden="0" isisolated="0" left="309.533203125" locked="0" name="" note="" opacity="100" anchor="309.533203125,299.9921875/347.16796875,299.9921875/" leftdirection="309.533203125,299.9921875/347.16796875,299.9921875/" rightdirection="309.533203125,299.9921875/347.16796875,299.9921875/" pointtype="2/2/" polarity="1" sliced="0" stroked="-1" strokecap="1" strokecolor="1" strokecmykcolor="0,0,0,100" strokedashes="" strokedashoffset="0" strokejoin="1" strokemiterlimit="4" strokeoverprint="0" strokewidth="0.75" top="300.3671875" url="" width="37.634765625"/><pathitem artworkknockout="0" blendingmode="0" closed="0" evenodd="0" filled="0" guides="0" height="16.9150390625" hidden="0" isisolated="0" left="346.79296875" locked="0" name="" note="" opacity="100" anchor="347.16796875,299.6748046875/347.16796875,316.58984375/" leftdirection="347.16796875,299.6748046875/347.16796875,316.58984375/" rightdirection="347.16796875,299.6748046875/347.16796875,316.58984375/" pointtype="2/2/" polarity="1" sliced="0" stroked="-1" strokecap="1" strokecolor="1" strokecmykcolor="0,0,0,100" strokedashes="" strokedashoffset="0" strokejoin="1" strokemiterlimit="4" strokeoverprint="0" strokewidth="0.75" top="316.58984375" url="" width="0"/><pathitem artworkknockout="0" blendingmode="0" closed="0" evenodd="0" filled="0" guides="0" height="0" hidden="0" isisolated="0" left="315.0478515625" locked="0" name="" note="" opacity="100" anchor="315.0478515625,307.560546875/347.16796875,307.560546875/" leftdirection="315.0478515625,307.560546875/347.16796875,307.560546875/" rightdirection="315.0478515625,307.560546875/347.16796875,307.560546875/" pointtype="2/2/" polarity="1" sliced="0" stroked="-1" strokecap="1" strokecolor="1" strokecmykcolor="0,0,0,100" strokedashes="" strokedashoffset="0" strokejoin="1" strokemiterlimit="4" strokeoverprint="0" strokewidth="0.75" top="307.935546875" url="" width="32.1201171875"/><pathitem artworkknockout="0" blendingmode="0" closed="0" evenodd="0" filled="0" guides="0" height="0" hidden="0" isisolated="0" left="103.24951171875" locked="0" name="" note="" opacity="100" anchor="140.14306640625,317.5/103.24951171875,317.5/" leftdirection="140.14306640625,317.5/103.24951171875,317.5/" rightdirection="140.14306640625,317.5/103.24951171875,317.5/" pointtype="2/2/" polarity="1" sliced="0" stroked="-1" strokecap="1" strokecolor="1" strokecmykcolor="0,0,0,0" strokedashes="" strokedashoffset="0" strokejoin="1" strokemiterlimit="4" strokeoverprint="0" strokewidth="3" top="319" url="" width="36.8935546875"/><pathitem artworkknockout="0" blendingmode="0" closed="0" evenodd="0" filled="0" guides="0" height="0" hidden="0" isisolated="0" left="109.16259765625" locked="0" name="" note="" opacity="100" anchor="146.99462890625,300.90234375/109.16259765625,300.90234375/" leftdirection="146.99462890625,300.90234375/109.16259765625,300.90234375/" rightdirection="146.99462890625,300.90234375/109.16259765625,300.90234375/" pointtype="2/2/" polarity="1" sliced="0" stroked="-1" strokecap="1" strokecolor="1" strokecmykcolor="0,0,0,0" strokedashes="" strokedashoffset="0" strokejoin="1" strokemiterlimit="4" strokeoverprint="0" strokewidth="3" top="302.40234375" url="" width="37.83203125"/><pathitem artworkknockout="0" blendingmode="0" closed="0" evenodd="0" filled="0" guides="0" height="0" hidden="0" isisolated="0" left="109.16259765625" locked="0" name="" note="" opacity="100" anchor="141.38330078125,308.470703125/109.16259765625,308.470703125/" leftdirection="141.38330078125,308.470703125/109.16259765625,308.470703125/" rightdirection="141.38330078125,308.470703125/109.16259765625,308.470703125/" pointtype="2/2/" polarity="1" sliced="0" stroked="-1" strokecap="1" strokecolor="1" strokecmykcolor="0,0,0,0" strokedashes="" strokedashoffset="0" strokejoin="1" strokemiterlimit="4" strokeoverprint="0" strokewidth="3" top="309.970703125" url="" width="32.220703125"/><pathitem artworkknockout="0" blendingmode="0" closed="0" evenodd="0" filled="0" guides="0" height="0" hidden="0" isisolated="0" left="105.13623046875" locked="0" name="" note="" opacity="100" anchor="140.92236328125,317.5/105.13623046875,317.5/" leftdirection="140.92236328125,317.5/105.13623046875,317.5/" rightdirection="140.92236328125,317.5/105.13623046875,317.5/" pointtype="2/2/" polarity="1" sliced="0" stroked="-1" strokecap="1" strokecolor="1" strokecmykcolor="0,0,0,100" strokedashes="" strokedashoffset="0" strokejoin="1" strokemiterlimit="4" strokeoverprint="0" strokewidth="0.75" top="317.875" url="" width="35.7861328125"/><pathitem artworkknockout="0" blendingmode="0" closed="0" evenodd="0" filled="0" guides="0" height="0" hidden="0" isisolated="0" left="110.80224609375" locked="0" name="" note="" opacity="100" anchor="148.43701171875,300.90234375/110.80224609375,300.90234375/" leftdirection="148.43701171875,300.90234375/110.80224609375,300.90234375/" rightdirection="148.43701171875,300.90234375/110.80224609375,300.90234375/" pointtype="2/2/" polarity="1" sliced="0" stroked="-1" strokecap="1" strokecolor="1" strokecmykcolor="0,0,0,100" strokedashes="" strokedashoffset="0" strokejoin="1" strokemiterlimit="4" strokeoverprint="0" strokewidth="0.75" top="301.27734375" url="" width="37.634765625"/><pathitem artworkknockout="0" blendingmode="0" closed="0" evenodd="0" filled="0" guides="0" height="16.9150390625" hidden="0" isisolated="0" left="110.42724609375" locked="0" name="" note="" opacity="100" anchor="110.80224609375,300.5849609375/110.80224609375,317.5/" leftdirection="110.80224609375,300.5849609375/110.80224609375,317.5/" rightdirection="110.80224609375,300.5849609375/110.80224609375,317.5/" pointtype="2/2/" polarity="1" sliced="0" stroked="-1" strokecap="1" strokecolor="1" strokecmykcolor="0,0,0,100" strokedashes="" strokedashoffset="0" strokejoin="1" strokemiterlimit="4" strokeoverprint="0" strokewidth="0.75" top="317.5" url="" width="0"/><pathitem artworkknockout="0" blendingmode="0" closed="0" evenodd="0" filled="0" guides="0" height="0" hidden="0" isisolated="0" left="110.80224609375" locked="0" name="" note="" opacity="100" anchor="142.92236328125,308.470703125/110.80224609375,308.470703125/" leftdirection="142.92236328125,308.470703125/110.80224609375,308.470703125/" rightdirection="142.92236328125,308.470703125/110.80224609375,308.470703125/" pointtype="2/2/" polarity="1" sliced="0" stroked="-1" strokecap="1" strokecolor="1" strokecmykcolor="0,0,0,100" strokedashes="" strokedashoffset="0" strokejoin="1" strokemiterlimit="4" strokeoverprint="0" strokewidth="0.75" top="308.845703125" url="" width="32.1201171875"/><textart artworkknockout="0" blendingmode="0" hidden="0" isisolated="0" left="67.33447265625" locked="0" name="" opacity="100" position="67.33447265625,277.92578125" sliced="0" top="277.92578125" url="" height="9.62207" width="41.52246" kind="2" wrapped="0" autokerning="-1" baselineshift="0" direction="2" fillcmykcolor="0,0,0,100" fillcolor="1" filled="-1" font="ArialMT" leading="12" size="10" tracking="0">Primer G</textart></layer></indicateinfo><illustinfo id=""><graphic graphicname="B136141.eps" width="" height="" id=""/></illustinfo></tmc-illust>
