<?xml version="1.0" encoding="UTF-8"?>
<tmc-illust ai_version="11.0"><indicateinfo lang="english" name=""><layer artworkknockout="2" blendingmode="0" dimplacedimages="0" isisolated="0" locked="0" name="IndicateLayer" opacity="100" preview="-1" printable="-1" sliced="0" visible="-1"><textart artworkknockout="0" blendingmode="0" hidden="0" isisolated="0" left="352.525390625" locked="0" name="71200S" opacity="100" position="352.525390625,251.8193359375" sliced="0" top="251.8193359375" url="" height="10" width="141" kind="2" wrapped="0" autokerning="-1" baselineshift="0" direction="2" fillrgbcolor="0,0,0" fillcolor="3" filled="-1" font="ArialMT" leading="12" size="10" tracking="0">FRONT SEAT ASSEMBLY LH</textart><textart artworkknockout="0" blendingmode="0" hidden="0" isisolated="0" left="113.88916015625" locked="0" name="71910A" opacity="100" position="113.88916015625,617.587890625" sliced="0" top="617.587890625" url="" height="10" width="179" kind="2" wrapped="0" autokerning="-1" baselineshift="0" direction="2" fillrgbcolor="0,0,0" fillcolor="3" filled="-1" font="ArialMT" leading="12" size="10" tracking="0">FRONT SEAT HEADREST ASSEMBLY</textart><textart artworkknockout="0" blendingmode="0" hidden="0" isisolated="0" left="152.4599609375" locked="0" name="89178A" opacity="100" position="152.4599609375,501.1357421875" sliced="0" top="501.1357421875" url="" height="11.56885" width="122.5815" kind="2" wrapped="0" autokerning="-1" baselineshift="0" direction="2" fillrgbcolor="0,0,0" fillcolor="3" filled="-1" font="ArialMT" leading="12" size="10" tracking="0">SEAT POSITION SENSOR</textart><pathitem artworkknockout="0" blendingmode="0" closed="0" evenodd="0" filled="0" guides="0" height="93.39404296875" hidden="0" isisolated="0" left="483.3671875" locked="0" name="" note="" opacity="100" anchor="496.8193359375,489.7685546875/483.7421875,502.845703125/483.7421875,583.16259765625/" leftdirection="496.8193359375,489.7685546875/483.7421875,502.845703125/483.7421875,583.16259765625/" rightdirection="496.8193359375,489.7685546875/483.7421875,502.845703125/483.7421875,583.16259765625/" pointtype="1/1/1/" polarity="1" sliced="0" stroked="-1" strokecap="1" strokecolor="3" strokergbcolor="0,0,0" strokedashes="" strokedashoffset="0" strokejoin="1" strokemiterlimit="4" strokeoverprint="0" strokewidth="0.75" top="583.16259765625" url="" width="13.0771484375"/><pathitem artworkknockout="0" blendingmode="0" closed="0" evenodd="0" filled="0" guides="0" height="111.26171875" hidden="0" isisolated="0" left="522.974609375" locked="0" name="" note="" opacity="100" anchor="523.349609375,493.421875/523.349609375,382.16015625/" leftdirection="523.349609375,493.421875/523.349609375,382.16015625/" rightdirection="523.349609375,493.421875/523.349609375,382.16015625/" pointtype="1/1/" polarity="1" sliced="0" stroked="-1" strokecap="1" strokecolor="3" strokergbcolor="0,0,0" strokedashes="" strokedashoffset="0" strokejoin="1" strokemiterlimit="4" strokeoverprint="0" strokewidth="0.75" top="493.421875" url="" width="0"/><pathitem artworkknockout="0" blendingmode="0" closed="0" evenodd="0" filled="0" guides="0" height="0" hidden="0" isisolated="0" left="291.19677734375" locked="0" name="" note="" opacity="100" anchor="291.19677734375,611.81787109375/331.546875,611.81787109375/" leftdirection="291.19677734375,611.81787109375/331.546875,611.81787109375/" rightdirection="291.19677734375,611.81787109375/331.546875,611.81787109375/" pointtype="1/1/" polarity="1" sliced="0" stroked="-1" strokecap="1" strokecolor="3" strokergbcolor="0,0,0" strokedashes="" strokedashoffset="0" strokejoin="1" strokemiterlimit="4" strokeoverprint="0" strokewidth="0.75" top="612.19287109375" url="" width="40.35009765625"/><pathitem artworkknockout="0" blendingmode="0" closed="0" evenodd="0" filled="0" guides="0" height="39.79443359375" hidden="0" isisolated="0" left="81.7041015625" locked="0" name="" note="" opacity="100" anchor="93.12158203125,441.88818359375/82.0791015625,452.9306640625/82.0791015625,481.6826171875/" leftdirection="93.12158203125,441.88818359375/82.0791015625,452.9306640625/82.0791015625,481.6826171875/" rightdirection="93.12158203125,441.88818359375/82.0791015625,452.9306640625/82.0791015625,481.6826171875/" pointtype="1/1/1/" polarity="1" sliced="0" stroked="-1" strokecap="1" strokecolor="3" strokergbcolor="0,0,0" strokedashes="" strokedashoffset="0" strokejoin="1" strokemiterlimit="4" strokeoverprint="0" strokewidth="0.75" top="481.6826171875" url="" width="11.04248046875"/><pathitem artworkknockout="0" blendingmode="0" closed="0" evenodd="0" filled="0" guides="0" height="25.05859375" hidden="0" isisolated="0" left="86.5576171875" locked="0" name="" note="" opacity="100" anchor="86.9326171875,361.6787109375/86.9326171875,386.7373046875/" leftdirection="86.9326171875,361.6787109375/86.9326171875,386.7373046875/" rightdirection="86.9326171875,361.6787109375/86.9326171875,386.7373046875/" pointtype="1/1/" polarity="1" sliced="0" stroked="-1" strokecap="1" strokecolor="3" strokergbcolor="0,0,0" strokedashes="" strokedashoffset="0" strokejoin="1" strokemiterlimit="4" strokeoverprint="0" strokewidth="0.75" top="386.7373046875" url="" width="0"/><pathitem artworkknockout="0" blendingmode="0" closed="0" evenodd="0" filled="0" guides="0" height="109.587890625" hidden="0" isisolated="0" left="112.0009765625" locked="0" name="" note="" opacity="100" anchor="150.16015625,318.763671875/112.3759765625,280.9794921875/112.3759765625,209.17578125/" leftdirection="150.16015625,318.763671875/112.3759765625,280.9794921875/112.3759765625,209.17578125/" rightdirection="150.16015625,318.763671875/112.3759765625,280.9794921875/112.3759765625,209.17578125/" pointtype="1/1/1/" polarity="-1" sliced="0" stroked="-1" strokecap="1" strokecolor="3" strokergbcolor="0,0,0" strokedashes="" strokedashoffset="0" strokejoin="1" strokemiterlimit="4" strokeoverprint="0" strokewidth="0.75" top="319.029296875" url="" width="37.7841796875"/><pathitem artworkknockout="0" blendingmode="0" closed="0" evenodd="0" filled="0" guides="0" height="61.21484375" hidden="0" isisolated="0" left="153.82373046875" locked="0" name="" note="" opacity="100" anchor="154.0888671875,421.578125/197.9306640625,465.419921875/197.9306640625,482.79296875/" leftdirection="154.0888671875,421.578125/197.9306640625,465.419921875/197.9306640625,482.79296875/" rightdirection="154.0888671875,421.578125/197.9306640625,465.419921875/197.9306640625,482.79296875/" pointtype="1/1/1/" polarity="-1" sliced="0" stroked="-1" strokecap="1" strokecolor="3" strokergbcolor="0,0,0" strokedashes="" strokedashoffset="0" strokejoin="1" strokemiterlimit="4" strokeoverprint="0" strokewidth="0.75" top="482.79296875" url="" width="43.841796875"/><pathitem artworkknockout="0" blendingmode="0" closed="-1" evenodd="0" filled="0" guides="0" height="13.46484375" hidden="0" isisolated="0" left="60.62109375" locked="0" name="" note="" opacity="100" anchor="153.2470703125,124.9912109375/61.12109375,124.9912109375/61.12109375,138.4560546875/153.2470703125,138.4560546875/" leftdirection="153.2470703125,124.9912109375/61.12109375,124.9912109375/61.12109375,138.4560546875/153.2470703125,138.4560546875/" rightdirection="153.2470703125,124.9912109375/61.12109375,124.9912109375/61.12109375,138.4560546875/153.2470703125,138.4560546875/" pointtype="2/2/2/2/" polarity="1" sliced="0" stroked="-1" strokecap="1" strokecolor="2" strokegraycolor="100" strokedashes="" strokedashoffset="0" strokejoin="1" strokemiterlimit="4" strokeoverprint="0" strokewidth="1" top="138.9560546875" url="" width="92.1259765625"/><textart artworkknockout="0" blendingmode="0" hidden="0" isisolated="0" left="62.177734375" locked="0" name="" opacity="100" position="62.177734375,137.5546875" sliced="0" top="137.5546875" url="" height="12.04297" width="89.41992" kind="2" wrapped="0" autokerning="-1" baselineshift="0" direction="1" fillrgbcolor="0,0,0" fillcolor="3" filled="-1" font="ArialMT" leading="12" size="10" tracking="0">N*m (kgf*cm, ft.*lbf)</textart><textart artworkknockout="0" blendingmode="0" hidden="0" isisolated="0" left="154.607421875" locked="0" name="" opacity="100" position="154.607421875,138.1787109375" sliced="0" top="138.1787109375" url="" height="12.04297" width="89.4209" kind="2" wrapped="0" autokerning="-1" baselineshift="0" direction="1" fillrgbcolor="0,0,0" fillcolor="3" filled="-1" font="ArialMT" leading="12" size="10" tracking="0">: Specified torque</textart><pathitem artworkknockout="0" blendingmode="0" closed="-1" evenodd="0" filled="-1" fillcolor="2" fillgraycolor="0" filloverprint="0" guides="0" height="13.9892578125" hidden="0" isisolated="0" left="45.154296875" locked="0" name="" note="" opacity="100" anchor="117.298828125,482.27783203125/45.654296875,482.27783203125/45.654296875,496.26708984375/117.298828125,496.26708984375/" leftdirection="117.298828125,482.27783203125/45.654296875,482.27783203125/45.654296875,496.26708984375/117.298828125,496.26708984375/" rightdirection="117.298828125,482.27783203125/45.654296875,482.27783203125/45.654296875,496.26708984375/117.298828125,496.26708984375/" pointtype="2/2/2/2/" polarity="1" sliced="0" stroked="-1" strokecap="1" strokecolor="2" strokegraycolor="100" strokedashes="" strokedashoffset="0" strokejoin="1" strokemiterlimit="4" strokeoverprint="0" strokewidth="1" top="496.76708984375" url="" width="71.64453125"/><textart artworkknockout="0" blendingmode="0" hidden="0" isisolated="0" left="48.5732421875" locked="0" name="" opacity="100" position="48.5732421875,493.73193359375" sliced="0" top="493.73193359375" url="" height="9.287109" width="66.72559" kind="2" wrapped="0" autokerning="-1" baselineshift="0" direction="1" fillrgbcolor="0,0,0" fillcolor="3" filled="-1" font="Arial-BoldMT" leading="9.60000038146973" size="8" tracking="0">8.0 (82, 71 in.*lbf)</textart><pathitem artworkknockout="0" blendingmode="0" closed="-1" evenodd="0" filled="0" guides="0" height="12.669921875" hidden="0" isisolated="0" left="87.34912109375" locked="0" name="" note="" opacity="100" anchor="136.6103515625,196.6591796875/87.84912109375,196.6591796875/87.84912109375,209.3291015625/136.6103515625,209.3291015625/" leftdirection="136.6103515625,196.6591796875/87.84912109375,196.6591796875/87.84912109375,209.3291015625/136.6103515625,209.3291015625/" rightdirection="136.6103515625,196.6591796875/87.84912109375,196.6591796875/87.84912109375,209.3291015625/136.6103515625,209.3291015625/" pointtype="2/2/2/2/" polarity="1" sliced="0" stroked="-1" strokecap="1" strokecolor="3" strokergbcolor="0,0,0" strokedashes="" strokedashoffset="0" strokejoin="1" strokemiterlimit="4" strokeoverprint="0" strokewidth="1" top="209.8291015625" url="" width="48.76123046875"/><textart artworkknockout="0" blendingmode="0" hidden="0" isisolated="0" left="89.38232421875" locked="0" name="" opacity="100" position="89.38232421875,207.9462890625" sliced="0" top="207.9462890625" url="" height="9.287109" width="45.05859" kind="2" wrapped="0" autokerning="-1" baselineshift="0" direction="1" fillrgbcolor="0,0,0" fillcolor="3" filled="-1" font="Arial-BoldMT" leading="9.60000038146973" size="8" tracking="0">37 (377, 27)</textart><pathitem artworkknockout="0" blendingmode="0" closed="-1" evenodd="0" filled="0" guides="0" height="12.669921875" hidden="0" isisolated="0" left="61.9951171875" locked="0" name="" note="" opacity="100" anchor="111.25634765625,386.8740234375/62.4951171875,386.8740234375/62.4951171875,399.5439453125/111.25634765625,399.5439453125/" leftdirection="111.25634765625,386.8740234375/62.4951171875,386.8740234375/62.4951171875,399.5439453125/111.25634765625,399.5439453125/" rightdirection="111.25634765625,386.8740234375/62.4951171875,386.8740234375/62.4951171875,399.5439453125/111.25634765625,399.5439453125/" pointtype="2/2/2/2/" polarity="1" sliced="0" stroked="-1" strokecap="1" strokecolor="3" strokergbcolor="0,0,0" strokedashes="" strokedashoffset="0" strokejoin="1" strokemiterlimit="4" strokeoverprint="0" strokewidth="1" top="400.0439453125" url="" width="48.76123046875"/><textart artworkknockout="0" blendingmode="0" hidden="0" isisolated="0" left="64.0283203125" locked="0" name="" opacity="100" position="64.0283203125,398.1611328125" sliced="0" top="398.1611328125" url="" height="9.287109" width="45.05859" kind="2" wrapped="0" autokerning="-1" baselineshift="0" direction="1" fillrgbcolor="0,0,0" fillcolor="3" filled="-1" font="Arial-BoldMT" leading="9.60000038146973" size="8" tracking="0">37 (377, 27)</textart><pathitem artworkknockout="0" blendingmode="0" closed="-1" evenodd="0" filled="0" guides="0" height="12.669921875" hidden="0" isisolated="0" left="458.349609375" locked="0" name="" note="" opacity="100" anchor="507.6103515625,583.6591796875/458.849609375,583.6591796875/458.849609375,596.3291015625/507.6103515625,596.3291015625/" leftdirection="507.6103515625,583.6591796875/458.849609375,583.6591796875/458.849609375,596.3291015625/507.6103515625,596.3291015625/" rightdirection="507.6103515625,583.6591796875/458.849609375,583.6591796875/458.849609375,596.3291015625/507.6103515625,596.3291015625/" pointtype="2/2/2/2/" polarity="1" sliced="0" stroked="-1" strokecap="1" strokecolor="3" strokergbcolor="0,0,0" strokedashes="" strokedashoffset="0" strokejoin="1" strokemiterlimit="4" strokeoverprint="0" strokewidth="1" top="596.8291015625" url="" width="48.7607421875"/><textart artworkknockout="0" blendingmode="0" hidden="0" isisolated="0" left="460.3828125" locked="0" name="" opacity="100" position="460.3828125,594.9462890625" sliced="0" top="594.9462890625" url="" height="9.287109" width="45.05859" kind="2" wrapped="0" autokerning="-1" baselineshift="0" direction="1" fillrgbcolor="0,0,0" fillcolor="3" filled="-1" font="Arial-BoldMT" leading="9.60000038146973" size="8" tracking="0">37 (377, 27)</textart><pathitem artworkknockout="0" blendingmode="0" closed="-1" evenodd="0" filled="0" guides="0" height="12.669921875" hidden="0" isisolated="0" left="426.349609375" locked="0" name="" note="" opacity="100" anchor="475.6103515625,461.6591796875/426.849609375,461.6591796875/426.849609375,474.3291015625/475.6103515625,474.3291015625/" leftdirection="475.6103515625,461.6591796875/426.849609375,461.6591796875/426.849609375,474.3291015625/475.6103515625,474.3291015625/" rightdirection="475.6103515625,461.6591796875/426.849609375,461.6591796875/426.849609375,474.3291015625/475.6103515625,474.3291015625/" pointtype="2/2/2/2/" polarity="1" sliced="0" stroked="-1" strokecap="1" strokecolor="3" strokergbcolor="0,0,0" strokedashes="" strokedashoffset="0" strokejoin="1" strokemiterlimit="4" strokeoverprint="0" strokewidth="1" top="474.8291015625" url="" width="48.7607421875"/><textart artworkknockout="0" blendingmode="0" hidden="0" isisolated="0" left="428.3828125" locked="0" name="" opacity="100" position="428.3828125,472.9462890625" sliced="0" top="472.9462890625" url="" height="9.287109" width="45.05859" kind="2" wrapped="0" autokerning="-1" baselineshift="0" direction="1" fillrgbcolor="0,0,0" fillcolor="3" filled="-1" font="Arial-BoldMT" leading="9.60000038146973" size="8" tracking="0">37 (377, 27)</textart><textart artworkknockout="0" blendingmode="0" hidden="0" isisolated="0" left="69" locked="0" name="" opacity="100" position="69,713.8896484375" sliced="0" top="713.8896484375" url="" height="14.11768" width="80.5" kind="2" wrapped="0" autokerning="-1" baselineshift="0" direction="2" fillrgbcolor="0,0,0" fillcolor="3" filled="-1" font="Arial-BoldMT" leading="12" size="10" tracking="0">for Power Seat:</textart><pathitem artworkknockout="0" blendingmode="0" closed="0" evenodd="0" filled="0" guides="0" height="54.0380859375" hidden="0" isisolated="0" left="277.1171875" locked="0" name="" note="" opacity="100" anchor="277.38232421875,301.6591796875/331.419921875,247.62109375/349.15234375,247.62109375/" leftdirection="277.38232421875,301.6591796875/331.419921875,247.62109375/349.15234375,247.62109375/" rightdirection="277.38232421875,301.6591796875/331.419921875,247.62109375/349.15234375,247.62109375/" pointtype="1/1/1/" polarity="-1" sliced="0" stroked="-1" strokecap="1" strokecolor="3" strokergbcolor="0,0,0" strokedashes="" strokedashoffset="0" strokejoin="1" strokemiterlimit="4" strokeoverprint="0" strokewidth="0.75" top="301.9248046875" url="" width="71.77001953125"/><pathitem artworkknockout="0" blendingmode="0" closed="0" evenodd="0" filled="0" guides="0" height="82.1806640625" hidden="0" isisolated="0" left="126.1904296875" locked="0" name="" note="" opacity="100" anchor="126.5654296875,434.708984375/126.5654296875,516.8896484375/" leftdirection="126.5654296875,434.708984375/126.5654296875,516.8896484375/" rightdirection="126.5654296875,434.708984375/126.5654296875,516.8896484375/" pointtype="1/1/" polarity="1" sliced="0" stroked="-1" strokecap="1" strokecolor="3" strokergbcolor="0,0,0" strokedashes="" strokedashoffset="0" strokejoin="1" strokemiterlimit="4" strokeoverprint="0" strokewidth="0.75" top="516.8896484375" url="" width="0"/><textart artworkknockout="0" blendingmode="0" hidden="0" isisolated="0" left="46" locked="0" name="" opacity="100" position="46,538.3896484375" sliced="0" top="538.3896484375" url="" height="11.5" width="221.7813" kind="2" wrapped="0" autokerning="-1" baselineshift="0" direction="2" fillrgbcolor="0,0,0" fillcolor="3" filled="-1" font="ArialMT" leading="12" size="10" tracking="0">SEAT SLIDE POSITION SENSOR PROTECTOR</textart><pathitem artworkknockout="0" blendingmode="0" closed="0" evenodd="0" filled="0" guides="0" height="116.599609375" hidden="0" isisolated="0" left="370.533203125" locked="0" name="" note="" opacity="100" anchor="451.1513671875,550.35595703125/399.68359375,666.95556640625/370.533203125,666.95556640625/" leftdirection="451.1513671875,550.35595703125/399.68359375,666.95556640625/370.533203125,666.95556640625/" rightdirection="451.1513671875,550.35595703125/399.68359375,666.95556640625/370.533203125,666.95556640625/" pointtype="1/1/1/" polarity="-1" sliced="0" stroked="-1" strokecap="1" strokecolor="3" strokergbcolor="0,0,0" strokedashes="" strokedashoffset="0" strokejoin="1" strokemiterlimit="4" strokeoverprint="0" strokewidth="0.75" top="667.33056640625" url="" width="80.6181640625"/><pathitem artworkknockout="0" blendingmode="0" closed="0" evenodd="0" filled="0" guides="0" height="49.20849609375" hidden="0" isisolated="0" left="437.62109375" locked="0" name="" note="" opacity="100" anchor="437.88671875,523.2744140625/451.1806640625,509.98046875/451.1806640625,474.06591796875/" leftdirection="437.88671875,523.2744140625/451.1806640625,509.98046875/451.1806640625,474.06591796875/" rightdirection="437.88671875,523.2744140625/451.1806640625,509.98046875/451.1806640625,474.06591796875/" pointtype="1/1/1/" polarity="1" sliced="0" stroked="-1" strokecap="1" strokecolor="3" strokergbcolor="0,0,0" strokedashes="" strokedashoffset="0" strokejoin="1" strokemiterlimit="4" strokeoverprint="0" strokewidth="0.75" top="523.53955078125" url="" width="13.2939453125"/><textart artworkknockout="0" blendingmode="0" hidden="0" isisolated="0" left="428" locked="0" name="72138B" opacity="100" position="428,376.8896484375" sliced="0" top="376.8896484375" url="" height="10" width="120" kind="2" wrapped="0" autokerning="-1" baselineshift="0" direction="2" fillrgbcolor="0,0,0" fillcolor="3" filled="-1" font="ArialMT" leading="12" size="10" tracking="0">SEAT TRACK COVER LH</textart><textart artworkknockout="0" blendingmode="0" hidden="0" isisolated="0" left="244" locked="0" name="72137B" opacity="100" position="244,672.8896484375" sliced="0" top="672.8896484375" url="" height="10" width="136.4004" kind="2" wrapped="0" autokerning="-1" baselineshift="0" direction="2" fillrgbcolor="0,0,0" fillcolor="3" filled="-1" font="ArialMT" leading="12" size="10" tracking="0">SEAT TRACK COVER RH</textart></layer></indicateinfo><illustinfo id=""><graphic graphicname="C133890.eps" width="" height="" id=""/></illustinfo></tmc-illust>
